fsql/__init__.py
fsql/api.py
fsql/column_parser.py
fsql/daterange_utils.py
fsql/deser.py
fsql/deser_dask.py
fsql/partition.py
fsql/partition_discovery.py
fsql/py.typed
fsql/query.py
fsql-0.23.0.dist-info/LICENSE
fsql-0.23.0.dist-info/METADATA
fsql-0.23.0.dist-info/WHEEL
fsql-0.23.0.dist-info/top_level.txt
fsql-0.23.0.dist-info/RECORD
