Metadata-Version: 2.1
Name: fsql
Version: 0.23.0
Summary: Metastore-like capabilities for various filesystems
License: " BSD-3-Clause"
Classifier: Programming Language :: Python :: 3
Classifier: Operating System :: OS Independent
Requires-Python: >=3.8
License-File: LICENSE
Requires-Dist: pandas
Provides-Extra: dask
Requires-Dist: dask ; extra == 'dask'
Provides-Extra: s3
Requires-Dist: fsspec[s3] >=2022.5.0 ; extra == 's3'
Provides-Extra: test
Requires-Dist: coverage ; extra == 'test'
Requires-Dist: fastparquet ; extra == 'test'
Requires-Dist: pyarrow ; extra == 'test'
Requires-Dist: moto ; extra == 'test'
Requires-Dist: pytest ; extra == 'test'
Requires-Dist: fsspec[s3] >=2022.5.0 ; extra == 'test'
Requires-Dist: openpyxl ; extra == 'test'
Requires-Dist: dask ; extra == 'test'
Provides-Extra: xlsx
Requires-Dist: openpyxl ; extra == 'xlsx'
